daily_reflection-0.2.1.data/scripts/daily-reflection
reflect/__init__.py
reflect/actions.py
reflect/daily_reflection.py
reflect/encrypted_json_storage.py
reflect/menus.py
reflect/style.py
reflect/version.py
daily_reflection-0.2.1.dist-info/LICENSE
daily_reflection-0.2.1.dist-info/METADATA
daily_reflection-0.2.1.dist-info/WHEEL
daily_reflection-0.2.1.dist-info/top_level.txt
daily_reflection-0.2.1.dist-info/RECORD
