Metadata-Version: 2.1
Name: daily-reflection
Version: 0.2.1
Summary: A small command-line tool that helps you conduct your daily morning/evening reflection.
Home-page: https://github.com/stefanthaler/maildaily-reflection
Author: Stefan Thaler
Author-email: bruthaler@gmail.com
License: UNKNOWN
Platform: UNKNOWN
Classifier: Programming Language :: Python :: 3
Classifier: License :: OSI Approved :: MIT License
Classifier: Operating System :: OS Independent
Requires-Dist: ptpython (==3.0.2)
Requires-Dist: pycryptodome (==3.9.7)
Requires-Dist: tinydb-encrypted-jsonstorage (==0.0.2)
Requires-Dist: tinydb (==3.15.2)
